pyobs_alpaca/__init__.py
pyobs_alpaca/device.py
pyobs_alpaca/dome.py
pyobs_alpaca/focuser.py
pyobs_alpaca/telescope.py
pyobs_alpaca-1.1.2.dist-info/METADATA
pyobs_alpaca-1.1.2.dist-info/WHEEL
pyobs_alpaca-1.1.2.dist-info/licenses/LICENSE
pyobs_alpaca-1.1.2.dist-info/RECORD
